beancount_bot/__init__.py
beancount_bot/__version__.py
beancount_bot/bot.py
beancount_bot/config.py
beancount_bot/dispatcher.py
beancount_bot/i18n.py
beancount_bot/main.py
beancount_bot/session.py
beancount_bot/session_config.py
beancount_bot/task.py
beancount_bot/transaction.py
beancount_bot/util.py
beancount_bot/builtin/__init__.py
beancount_bot/builtin/daily_command_task.py
beancount_bot/builtin/template_dispatcher.py
beancount_bot-1.2.1.dist-info/LICENSE
beancount_bot-1.2.1.dist-info/METADATA
beancount_bot-1.2.1.dist-info/WHEEL
beancount_bot-1.2.1.dist-info/entry_points.txt
beancount_bot-1.2.1.dist-info/top_level.txt
beancount_bot-1.2.1.dist-info/RECORD
