Metadata-Version: 2.1
Name: beancount-bot
Version: 1.2.1
Summary: A telegram bot designed for Beancount
Home-page: https://github.com/kaaass/beancount_bot
Author: KAAAsS
Author-email: admin@kaaass.net
License: MIT
Platform: UNKNOWN
Classifier: Programming Language :: Python :: 3
Classifier: License :: OSI Approved :: MIT License
Classifier: Operating System :: OS Independent
Requires-Python: >=3.6.0
License-File: LICENSE
Requires-Dist: beancount (==2.*)
Requires-Dist: click (==8.0.4)
Requires-Dist: pyTelegramBotAPI (==4.1.0)
Requires-Dist: PyYAML (==5.4.1)
Requires-Dist: schedule (==1.1.0)
